mirage/__init__.py
mirage/global_config.py
mirage/graph_dataset.py
mirage/kernel.py
mirage/profiler.py
mirage/threadblock.py
mirage/triton_profiler.py
mirage/utils.py
mirage/version.py
mirage/visualizer.py
mirage/yica_auto_tuner.py
mirage/yica_distributed.py
mirage/yica_distributed_optimizer.py
mirage/yica_kernel_generator_demo.py
mirage/yica_llama_optimizer.py
mirage/yica_optimizer.py
mirage/yica_performance_monitor.py
mirage/yica_performance_monitor_demo.py
mirage/yica_pytorch_backend.py
yica_mirage-1.0.0.dist-info/licenses/LICENSE
yica_mirage-1.0.0.dist-info/METADATA
yica_mirage-1.0.0.dist-info/WHEEL
yica_mirage-1.0.0.dist-info/entry_points.txt
yica_mirage-1.0.0.dist-info/top_level.txt
yica_mirage-1.0.0.dist-info/RECORD
