Metadata-Version: 2.4
Name: yica-mirage
Version: 1.0.0
Summary: YICA-Mirage: AI Computing Optimization Framework for In-Memory Computing Architecture
Home-page: https://github.com/yica-ai/yica-mirage
Author: YICA Team
Author-email: YICA Team <contact@yica.ai>
Maintainer-email: YICA Team <contact@yica.ai>
License: MIT License
Project-URL: Homepage, https://github.com/yica-ai/yica-mirage
Project-URL: Documentation, https://yica-mirage.readthedocs.io/
Project-URL: Repository, https://github.com/yica-ai/yica-mirage.git
Project-URL: Bug Tracker, https://github.com/yica-ai/yica-mirage/issues
Project-URL: Changelog, https://github.com/yica-ai/yica-mirage/blob/main/CHANGELOG.md
Keywords: ai,optimization,compiler,triton,yica,mirage,deep-learning,in-memory-computing
Classifier: Development Status :: 4 - Beta
Classifier: Intended Audience :: Developers
Classifier: Intended Audience :: Science/Research
Classifier: License :: OSI Approved :: MIT License
Classifier: Operating System :: POSIX :: Linux
Classifier: Operating System :: MacOS :: MacOS X
Classifier: Operating System :: Microsoft :: Windows
Classifier: Programming Language :: Python :: 3
Classifier: Programming Language :: Python :: 3.8
Classifier: Programming Language :: Python :: 3.9
Classifier: Programming Language :: Python :: 3.10
Classifier: Programming Language :: Python :: 3.11
Classifier: Programming Language :: Python :: 3.12
Classifier: Programming Language :: C++
Classifier: Topic :: Scientific/Engineering :: Artificial Intelligence
Classifier: Topic :: Software Development :: Compilers
Classifier: Topic :: System :: Hardware
Requires-Python: >=3.8
License-File: LICENSE
Requires-Dist: numpy>=1.19.0
Requires-Dist: torch>=1.12.0
Requires-Dist: triton>=2.0.0
Requires-Dist: z3-solver>=4.8.0
Requires-Dist: pybind11>=2.6.0
Provides-Extra: dev
Requires-Dist: pytest>=6.0; extra == "dev"
Requires-Dist: pytest-cov>=3.0; extra == "dev"
Requires-Dist: black>=21.0; extra == "dev"
Requires-Dist: flake8>=3.8; extra == "dev"
Requires-Dist: mypy>=0.900; extra == "dev"
Requires-Dist: sphinx>=4.0; extra == "dev"
Requires-Dist: sphinx-rtd-theme>=1.0; extra == "dev"
Requires-Dist: pre-commit>=2.15; extra == "dev"
Provides-Extra: cuda
Requires-Dist: cupy>=9.0.0; extra == "cuda"
Requires-Dist: nvidia-ml-py>=11.0.0; extra == "cuda"
Provides-Extra: rocm
Requires-Dist: torch-rocm>=1.12.0; extra == "rocm"
Provides-Extra: all
Requires-Dist: yica-mirage[cuda,dev]; extra == "all"
Dynamic: author
Dynamic: home-page
Dynamic: license-file
Dynamic: requires-python
